[ { "domain":"hello.paddy233-blog.ml","subject":"","start":"","expire":"","issuer":"","status":"失效","statuscolor":"error","check":"2023-04-23 00:22:34","remain":"0"},{"domain":"blog.paddy.eu.org","subject":"CN=paddy.eu.org","start":"Apr 22 03:57:09 2023 GMT","expire":"Jul 21 03:57:08 2023 GMT","issuer":"C=US; O=Google Trust Services LLC; CN=GTS CA 1P5","status":"无效","statuscolor":"error","check":"2023-04-23 00:22:35","remain":"89"},{"domain":"github.paddy.cf","subject":"","start":"","expire":"","issuer":"","status":"失效","statuscolor":"error","check":"2023-04-23 00:22:35","remain":"0"},{"domain":"paddy.ml","subject":"","start":"","expire":"","issuer":"","status":"失效","statuscolor":"error","check":"2023-04-23 00:22:36","remain":"0" } ]
